MANIFEST.in
README.md
setup.py
hydralit_components/__init__.py
hydralit_components.egg-info/PKG-INFO
hydralit_components.egg-info/SOURCES.txt
hydralit_components.egg-info/dependency_links.txt
hydralit_components.egg-info/requires.txt
hydralit_components.egg-info/top_level.txt
hydralit_components/CookieManager/__init__.py
hydralit_components/CookieManager/frontend/build/asset-manifest.json
hydralit_components/CookieManager/frontend/build/bootstrap.min.css
hydralit_components/CookieManager/frontend/build/index.html
hydralit_components/CookieManager/frontend/build/static/js/2.a63ae2c6.chunk.js
hydralit_components/CookieManager/frontend/build/static/js/2.a63ae2c6.chunk.js.LICENSE.txt
hydralit_components/CookieManager/frontend/build/static/js/2.a63ae2c6.chunk.js.map
hydralit_components/CookieManager/frontend/build/static/js/main.83c402af.chunk.js
hydralit_components/CookieManager/frontend/build/static/js/main.83c402af.chunk.js.map
hydralit_components/CookieManager/frontend/build/static/js/runtime-main.4ea39c35.js
hydralit_components/CookieManager/frontend/build/static/js/runtime-main.4ea39c35.js.map
hydralit_components/Experimental/__init__.py
hydralit_components/Experimental/experiments.py
hydralit_components/Loaders/__init__.py
hydralit_components/Loaders/loaders.py
hydralit_components/NavBar/__init__.py
hydralit_components/NavBar/frontend/build/asset-manifest.json
hydralit_components/NavBar/frontend/build/bootstrap.min.css.map
hydralit_components/NavBar/frontend/build/index.html
hydralit_components/NavBar/frontend/build/jquery-3.6.0.slim.min.js
hydralit_components/NavBar/frontend/build/mdb.min.js
hydralit_components/NavBar/frontend/build/popper.min.js
hydralit_components/NavBar/frontend/build/popper.min.js.map
hydralit_components/NavBar/frontend/build/precache-manifest.b5e829b4b8941a7569dc0e1dd938227f.js
hydralit_components/NavBar/frontend/build/service-worker.js
hydralit_components/NavBar/frontend/build/styling.js
hydralit_components/NavBar/frontend/build/fa5/LICENSE.txt
hydralit_components/NavBar/frontend/build/fa5/attribution.js
hydralit_components/NavBar/frontend/build/fa5/css/all.css
hydralit_components/NavBar/frontend/build/fa5/css/all.min.css
