Metadata-Version: 2.1
Name: hydralit-components
Version: 1.0.6
Summary: Components to use with or without the Hydralit package.
Home-page: https://github.com/tanglespace/hydralit_components
Author: Jackson Storm
Author-email: c6lculus8ntr0py@gmail.com
License: Apache 2
Project-URL: Documentation, https://github.com/tanglespace/hydralit_components
Project-URL: Source, https://github.com/tanglespace/hydralit_components
Project-URL: Tracker, https://github.com/tanglespace/hydralit_components/issues
Keywords: Streamlit,Web,Responsive,Deployment,Web Application,Presentation
Platform: UNKNOWN
Classifier: Operating System :: OS Independent
Classifier: Programming Language :: Python :: 3.6
Classifier: Programming Language :: Python :: 3.7
Classifier: Programming Language :: Python :: 3.8
Classifier: Programming Language :: Python :: 3.9
Requires-Python: >=3.6
